img2gif_aijinsol/__init__.py
img2gif_aijinsol/converter.py
img2gif_aijinsol-1.0.0.dist-info/LICENSE
img2gif_aijinsol-1.0.0.dist-info/METADATA
img2gif_aijinsol-1.0.0.dist-info/WHEEL
img2gif_aijinsol-1.0.0.dist-info/top_level.txt
img2gif_aijinsol-1.0.0.dist-info/RECORD
